lms_core/__init__.py
lms_core/calculator/__init__.py
lms_core/calculator/eligibility_calculator.py
lms_core/calculator/emi_calculator.py
lms_core/exceptions/__init__.py
lms_core/exceptions/lms_exception.py
lms_core/helpers/__init__.py
lms_core/helpers/loan_helper.py
lms_core/validator/__init__.py
lms_core/validator/loan_validator.py
lms_core/validator/payment_validator.py
lms_core/validator/user_validator.py
x23113383_loan_management_system-0.0.2.dist-info/LICENSE.txt
x23113383_loan_management_system-0.0.2.dist-info/METADATA
x23113383_loan_management_system-0.0.2.dist-info/WHEEL
x23113383_loan_management_system-0.0.2.dist-info/top_level.txt
x23113383_loan_management_system-0.0.2.dist-info/RECORD
