Metadata-Version: 2.1
Name: x23113383_loan_management_system
Version: 0.0.2
Summary: Loan Management System Library
Home-page: https://github.com/user-kranthi123/
Author: user-kranthi123
Author-email: kranthikumar.kphb@gmail.com
License: UNKNOWN
Platform: UNKNOWN
Classifier: Programming Language :: Python :: 3
Classifier: License :: OSI Approved :: MIT License
Classifier: Operating System :: OS Independent
Requires-Python: >=3.6
License-File: LICENSE.txt
